sentence_transmorgrifier/__init__.py
sentence_transmorgrifier/transmorgrify.py
sentence_transmorgrifier-0.1.0.dist-info/METADATA
sentence_transmorgrifier-0.1.0.dist-info/WHEEL
sentence_transmorgrifier-0.1.0.dist-info/licenses/LICENSE
sentence_transmorgrifier-0.1.0.dist-info/RECORD
