Metadata-Version: 2.4
Name: sentence_transmorgrifier
Version: 0.1.0
Summary: The Sentence Transmorgrifier is a framework to make text to text conversion models which uses a categorical gradient boost library, catboost, as its back end.
Project-URL: Homepage, https://github.com/JEdward7777/SentenceTransmogrifier
Project-URL: Issues, https://github.com/JEdward7777/SentenceTransmogrifier/issues
Author-email: Joshua Lansford <Joshua@Lansfords.com>
License-Expression: Apache-2.0
License-File: LICENSE
Classifier: License :: OSI Approved :: Apache Software License
Classifier: Operating System :: OS Independent
Classifier: Programming Language :: Python :: 3
Requires-Python: >=3.8
Requires-Dist: catboost
